cv2cuda/__init__.py
cv2cuda/decorator.py
cv2cuda/ffmpeg_process.py
cv2cuda/video_capture.py
cv2cuda/video_writer.py
cv2cuda/bin/__init__.py
cv2cuda/bin/main.py
cv2cuda/bin/parser.py
cv2cuda/tests/__init__.py
cv2cuda/tests/test.py
cv2cuda/tests/test_VideoWriter.py
cv2cuda/tests/test_timeit.py
cv2cuda/utils/__init__.py
cv2cuda/utils/components.py
cv2cuda/utils/cpu.py
cv2cuda/utils/gpu.py
cv2cuda-1.0.6.dist-info/METADATA
cv2cuda-1.0.6.dist-info/WHEEL
cv2cuda-1.0.6.dist-info/entry_points.txt
cv2cuda-1.0.6.dist-info/top_level.txt
cv2cuda-1.0.6.dist-info/RECORD
