Metadata-Version: 2.1
Name: cv2cuda
Version: 1.0.6
Requires-Python: >=3.7.0
Requires-Dist: opencv-python (>=3.4.8.29)
Requires-Dist: psutil
Provides-Extra: profile
Requires-Dist: pynvml ; extra == 'profile'
Requires-Dist: numpy ; extra == 'profile'
Provides-Extra: test
Requires-Dist: progressbar ; extra == 'test'
